{
  "_class": "symbolInstance",
  "booleanOperation": -1,
  "clippingMaskMode": 0,
  "do_objectID": "591C1CED-F7A3-443E-AAB2-91F3291B1AB3",
  "exportOptions": {
    "_class": "exportOptions",
    "do_objectID": "9FE052CE-97A9-464D-B633-FF15B346FA6B",
    "exportFormats": [
    ],
    "includedLayerIds": [
    ],
    "layerOptions": 0,
    "shouldTrim": false
  },
  "frame": {
    "_class": "rect",
    "constrainProportions": false,
    "do_objectID": "17926C83-5CE3-41F1-ABB8-66D0052EC716",
    "height": 46,
    "width": 146,
    "x": 28,
    "y": 14
  },
  "hasClippingMask": false,
  "horizontalSpacing": 0,
  "isFixedToViewport": false,
  "isFlippedHorizontal": false,
  "isFlippedVertical": false,
  "isLocked": false,
  "isVisible": true,
  "layerListExpandedType": 0,
  "name": "Logo/company_name",
  "nameIsFixed": false,
  "overrideValues": [
  ],
  "resizingConstraint": 63,
  "resizingType": 0,
  "rotation": 0,
  "scale": 1,
  "shouldBreakMaskChain": false,
  "style": {
    "_class": "style",
    "do_objectID": "0980436F-31BC-4BAF-9506-619A9380D7D9",
    "endMarkerType": 0,
    "miterLimit": 10,
    "startMarkerType": 0,
    "windingRule": 1
  },
  "symbolID": "82DAD5DC-0799-4752-B79E-CA9843E05F65",
  "verticalSpacing": 0
}